dmppl/VERSION
dmppl/__init__.py
dmppl/base.py
dmppl/bytePipe.py
dmppl/color.py
dmppl/fx.py
dmppl/math.py
dmppl/nd.py
dmppl/prng.py
dmppl/stats.py
dmppl/test.py
dmppl/toml.py
dmppl/vcd.py
dmppl/yaml.py
dmppl/experiments/__init__.py
dmppl/experiments/eva/__init__.py
dmppl/experiments/eva/eva.py
dmppl/experiments/eva/eva_common.py
dmppl/experiments/eva/eva_html_table.py
dmppl/experiments/eva/eva_httpd.py
dmppl/experiments/eva/eva_init.py
dmppl/experiments/eva/eva_svg_netgraph.py
dmppl/scripts/__init__.py
dmppl/scripts/beamer_times.py
dmppl/scripts/bytePipe_utils.py
dmppl/scripts/parvec.py
dmppl/scripts/plotCsv.py
dmppl/scripts/plotDistBytes.py
dmppl/scripts/svg2png.py
dmppl/scripts/vcd_utils.py
dmppl-0.2.0.dist-info/LICENSE
dmppl-0.2.0.dist-info/METADATA
dmppl-0.2.0.dist-info/WHEEL
dmppl-0.2.0.dist-info/entry_points.txt
dmppl-0.2.0.dist-info/top_level.txt
dmppl-0.2.0.dist-info/RECORD
