Metadata-Version: 2.1
Name: dmppl
Version: 0.2.0
Summary: Dave McEwan's Personal Python Library
Home-page: https://github.com/DaveMcEwan/dmppl/
Author: Dave McEwan
Author-email: cogitocumimpune@hotmail.com
License: UNKNOWN
Project-URL: Bug Reports, https://github.com/DaveMcEwan/dmppl/issues
Project-URL: Source, https://github.com/DaveMcEwan/dmppl/
Platform: UNKNOWN
Classifier: Development Status :: 3 - Alpha
Classifier: Intended Audience :: Developers
Classifier: Topic :: Scientific/Engineering
Classifier: Topic :: Scientific/Engineering :: Mathematics
Classifier: Topic :: Software Development
Classifier: Topic :: Software Development :: Libraries :: Python Modules
Classifier: License :: OSI Approved :: MIT License
Classifier: Programming Language :: Python :: 2.7
Classifier: Programming Language :: Python :: 3
Classifier: Programming Language :: Python :: 3.6
Classifier: Programming Language :: Python :: 3.7
Classifier: Programming Language :: Python :: 3.8
Requires-Python: >=2.7, !=3.0.*, !=3.1.*, !=3.2.*, !=3.3.*, !=3.4.*, <4
Requires-Dist: joblib (~=0.14.1)
Requires-Dist: numpy (~=1.16.5)
Requires-Dist: prettytable (~=0.7.2)
Requires-Dist: pyserial (~=3.4)
Requires-Dist: pyyaml (~=5.3.1)
Requires-Dist: toml (~=0.10.0)
Requires-Dist: coverage (~=5.0.4)
Requires-Dist: graphviz (~=0.13.2)
Requires-Dist: matplotlib (~=3.2.1)
Requires-Dist: mypy (>=0.770)
Requires-Dist: pydot (~=1.4.1)
Requires-Dist: seaborn (~=0.10.0)
Requires-Dist: tinyprog (==1.0.21)
